veryscrape/__init__.py
veryscrape/__main__.py
veryscrape/cli.py
veryscrape/items.py
veryscrape/process.py
veryscrape/scrape.py
veryscrape/session.py
veryscrape/veryscrape.py
veryscrape/wrappers.py
veryscrape/scrapers/__init__.py
veryscrape/scrapers/google.py
veryscrape/scrapers/reddit.py
veryscrape/scrapers/spider.py
veryscrape/scrapers/twingly.py
veryscrape/scrapers/twitter.py
veryscrape-0.1.3.dist-info/METADATA
veryscrape-0.1.3.dist-info/RECORD
veryscrape-0.1.3.dist-info/WHEEL
veryscrape-0.1.3.dist-info/entry_points.txt
veryscrape-0.1.3.dist-info/top_level.txt
