Metadata-Version: 2.1
Name: veryscrape
Version: 0.1.3
Summary: Simple time-series streaming of social media data
Home-page: https://github.com/sentrip/veryscrape
Author: Djordje Pepic
Author-email: djordje.m.pepic@gmail.com
License: GNU General Public License v3
Keywords: veryscrape
Platform: UNKNOWN
Classifier: Development Status :: 2 - Pre-Alpha
Classifier: Intended Audience :: Developers
Classifier: License :: OSI Approved :: GNU General Public License v3 (GPLv3)
Classifier: Natural Language :: English
Classifier: Programming Language :: Python :: 3.5
Classifier: Programming Language :: Python :: 3.6
Requires-Dist: Click (>=6.0)
Requires-Dist: aiohttp (>=2.3.10)
Requires-Dist: lxml (>=3.5.0)
Requires-Dist: async-timeout (==2.0.0)
Requires-Dist: aioauth-client (>=0.8.0)
Requires-Dist: fake-useragent (>=0.1.10)
Requires-Dist: newspaper3k (>=0.2.6)
Requires-Dist: twingly-search (>=2.1.1)
Requires-Dist: deprecation (>=2.0.2)
Requires-Dist: proxybroker (>=0.3.1)
Requires-Dist: redis (>=2.10.6)
